pctree/__init__.py
pctree/branches.py
pctree/core.py
pctree/display.py
pctree/generation.py
pctree/imputation.py
pctree/io.py
pctree/linalg_utils.py
pctree/logging_utils.py
pctree/persistent_homology.py
pctree/pruning.py
pctree/reweighting.py
pctree/subspace_clustering.py
pctree/subspace_sifting.py
pctree/training.py
pctree-0.0.12.dist-info/METADATA
pctree-0.0.12.dist-info/WHEEL
pctree-0.0.12.dist-info/top_level.txt
pctree-0.0.12.dist-info/RECORD
