Metadata-Version: 2.1
Name: pctree
Version: 0.0.12
Summary: Official Implementation of `Principal Component Trees` as referenced in the 2024 AAAI Paper `Principal Component Trees and their Persistent Homology`
Home-page: https://github.com/benkizaric/pctree
Author: Ben Kizaric
Author-email: benkizaric@gmail.com
License: MIT
Classifier: License :: OSI Approved :: MIT License
Classifier: Programming Language :: Python :: 3.10
Classifier: Operating System :: OS Independent
Requires-Python: >= 3.10
Requires-Dist: numpy >=1.24.0
Requires-Dist: scikit-learn >=1.2.0
Requires-Dist: scipy >=1.11.0
